README.md
setup.py
yoginth/__init__.py
yoginth/__main__.py
yoginth/yoginth.py
yoginth.egg-info/PKG-INFO
yoginth.egg-info/SOURCES.txt
yoginth.egg-info/dependency_links.txt
yoginth.egg-info/entry_points.txt
yoginth.egg-info/requires.txt
yoginth.egg-info/top_level.txt